Authors
ChangeLog
License
MANIFEST
setup.py
RosterUserTools.egg-info/PKG-INFO
RosterUserTools.egg-info/SOURCES.txt
RosterUserTools.egg-info/dependency_links.txt
RosterUserTools.egg-info/top_level.txt
docs/html/.buildinfo
docs/html/genindex.html
docs/html/index.html
docs/html/objects.inv
docs/html/py-modindex.html
docs/html/roster_user_tools.html
docs/html/search.html
docs/html/searchindex.js
docs/html/_modules/index.html
docs/html/_modules/roster_user_tools/action_flags.html
docs/html/_modules/roster_user_tools/cli_common_lib.html
docs/html/_modules/roster_user_tools/cli_record_lib.html
docs/html/_modules/roster_user_tools/core_flags.html
docs/html/_modules/roster_user_tools/data_flags.html
docs/html/_modules/roster_user_tools/roster_client_lib.html
docs/html/_sources/index.txt
docs/html/_sources/roster_user_tools.txt
docs/html/_static/ajax-loader.gif
docs/html/_static/basic.css
docs/html/_static/comment-bright.png
docs/html/_static/comment-close.png
docs/html/_static/comment.png
docs/html/_static/default.css
docs/html/_static/doctools.js
docs/html/_static/down-pressed.png
docs/html/_static/down.png
docs/html/_static/file.png
docs/html/_static/jquery.js
docs/html/_static/minus.png
docs/html/_static/plus.png
docs/html/_static/pygments.css
docs/html/_static/searchtools.js
docs/html/_static/sidebar.js
docs/html/_static/underscore.js
docs/html/_static/up-pressed.png
docs/html/_static/up.png
docs/html/_static/websupport.js
roster_user_tools/__init__.py
roster_user_tools/action_flags.py
roster_user_tools/cli_common_lib.py
roster_user_tools/cli_record_lib.py
roster_user_tools/core_flags.py
roster_user_tools/data_flags.py
roster_user_tools/roster_client_lib.py
scripts/dnsaddformattedrecords
scripts/dnscredential
scripts/dnslsacl
scripts/dnslsauditlog
scripts/dnslscnames
scripts/dnslsdnsservers
scripts/dnslshost
scripts/dnslsrecord
scripts/dnslsreservedwords
scripts/dnslsusergroup
scripts/dnslsviews
scripts/dnslszones
scripts/dnsmassadd
scripts/dnsmkacl
scripts/dnsmkdnsserver
scripts/dnsmkhost
scripts/dnsmkrecord
scripts/dnsmkreservedword
scripts/dnsmkusergroup
scripts/dnsmkview
scripts/dnsmkzone
scripts/dnsrmacl
