Metadata-Version: 1.0
Name: RosterUserTools
Version: 0.17
Summary: RosterUserTools are a set of command line tools for Roster
Home-page: http://code.google.com/p/roster-dns-management/
Author: Roster Development Team
Author-email: roster-discussion@googlegroups.com
License: BSD
Platform: UNKNOWN
Classifier: Development Status :: 4 - Beta
Classifier: Environment :: Console
Classifier: Intended Audience :: System Administrators
Classifier: License :: OSI Approved :: BSD License
Classifier: Operating System :: Unix
Classifier: Programming Language :: Python :: 2.5
Classifier: Topic :: Internet :: Name Service (DNS)
